{
  "company_name": "Razorpay",
  "company_slug": "razorpay",
  "company_logo_url": "/company-logos/razorpay.png",
  "job": {
    "title": "Solutions Engineer",
    "apply_url": "https://job-boards.greenhouse.io/razorpaysoftwareprivatelimited/jobs/4661194005",
    "location_display": "Kuala Lumpur, Malaysia",
    "work_mode": "on-site",
    "role_department": "engineering",
    "posted_date": "2026-04-13"
  },
  "jd": {
    "raw_text": "Back to jobs Solutions Engineer Malaysia Apply Razorpay is one of India\u2019s leading full-stack financial technology companies, powering the way businesses move, manage, and grow money. Founded in 2014 by Harshil Mathur and Shashank Kumar with a simple vision - to simplify payments for Indian businesses - we\u2019ve since grown into a fintech powerhouse driving India\u2019s digital payment revolution. Razorpay powers millions of businesses with a smarter, scalable stack that goes beyond transactions to help them truly build and grow. From building AI-native agentic payments, to AI-assisted fraud detection and real-time risk intelligence to automated reconciliation, smart payouts, and predictive financial insights, we are embedding intelligence across our stack to make money movement faster, safer, and more efficient. In close collaboration with ecosystem partners - including banks, networks, regulators - we are pioneering industry-first solutions that are shaping the next era of fintech Across India, Singapore and Malaysia, our products span everything from seamless checkouts to payroll automation - powering a fintech ecosystem that\u2019s redefining how money moves across Asia. Today, that ecosystem supports everyone from early-stage startups to some of India\u2019s largest enterprises, enabling them to accept, process, and disburse payments at scale while expanding into new ways of managing money more efficiently. Our scale speaks volumes: Razorpay processes $180+ billion in annualized transactions, powering leading businesses like Airbnb, Facebook, WhatsApp, Airtel, CRED, BookmyShow, Zomato, Swiggy, Lenskart, Mirae Asset Capital markets, Indian Oil, National Pension Scheme - and over 100 of India\u2019s unicorns. With strong roots in India and growing operations in Southeast Asia, we are shaping the next chapter of financial technology across the region. We are backed by global investors including GIC, Peak XV Partners (formerly Sequoia Capital India & SEA), Tiger Global, Ribbit Capital, Matrix Partners, MasterCard, and Salesforce Ventures, having raised over $740 million to date. Strategic acquisitions - including Ezetap (POS and offline payments), Curlec (Malaysia expansion), BillMe (digital invoicing), and POP (rewards-first UPI) - along with earlier moves in fraud prevention, payroll, and lending, have further strengthened our platform and widened our footprint across Asia. But what truly sets Razorpay apart is our culture. At Razorpay, ownership is our oxygen - you own what you build, with no micromanagement or red tape, just the runway to make your ideas fly. Learning is a lifestyle - if you\u2019re curious, you\u2019ll feel at home here. People > Pedigree - we hire for attitude, hustle, and hunger more than degrees. Transparency thrives over titles - this is where interns question CXOs and CXOs say \u201cthank you.\u201d Guided by our values of Customer First, Autonomy & Ownership, Agility with Integrity, Transparency, Challenging the status quo and a strong belief that Razorpay grows with Razors, you\u2019ll be part of a 3000+ strong team building not just products, but the financial infrastructure of the future. About Us As part of its ambitious growth strategy in Southeast Asia, Razorpay acquired Curlec in Malaysia. Since making the acquisition, Curlec by Razorpay has received an acquiring license by Bank Negara and is a registered member of Paynet. The Malaysia market presents a unique opportunity for Curlec by Razorpay due to its rapid digitalization and growing e-commerce ecosystem. Curlec aims to become the preferred payment partner for businesses across Malaysia, offering them the same level of reliability, security, and convenience that has made Razorpay a trusted name in India. We also live in Singapore with plans of expansion to Thailand, Indonesia and the rest of SEA. NOTE: This role is based in Malaysia. Please apply if you are authorised to work without a sponsorship. About the Role As the Solution Engineer, you will serve as the customer-facing advocate for Curlec by Razorpay suite of products, supporting prospects with technical implementation for large enterprises. This role reports to the Head of Integrations within the Business Engineering team at Razorpay. The individual will play a key role in ensuring the successful integration of Curlec\u2019s platform with merchants, enabling seamless payment solutions. Responsibilities This Individual should have a deep understanding of the entire product suite. Should be up-to-date in the technical knowledge and in-depth understanding of any coding language is a must. Responsible for implementation of the solutions provided by Curlec Razorpay for the Key Clients. Responsible to represent Curlec Razorpay from platform integration perspective with prospective merchants. Accountable to ensure successful implementation of platform integration between Curlec by Razorpay and merchants. Support the reactive queries and requests being raised by Merchants within an agreed turnaround time and quality standards. Read and respond to integration and platform documents shared by prospective customers. The individual will act as a key feedback channel for customer's product requirements/ expectations and will close the loop with the Product team on the same. In the case of product customisation requests from the clients, he/she would help validate the requirements. Requirements 2+ years of experience in product-based payments or SaaS platform integrations, implementation, or solutions in a customer-facing role. Bachelor\u2019s or Master\u2019s degree in Computer Science, Information Technology, or related fields. Hands-on experience with Java, .NET, PHP, Python, and JavaScript. Strong expertise in REST APIs. Strong ability to understand technical requirements and ensure seamless platform integration for enterprise clients. Excellent written and verbal communication skills, with strong presentation abilities. Preferably from Fintech background. Location & Commitments Permanent full time role based at our office - Kuala Lumpur (Mondays to Fridays) Razorpay believes in and follows an equal employment opportunity policy that doesn't discriminate on gender, religion, sexual orientation, colour, nationality, age, etc. We welcome interests and applications from all groups and communities across the globe. Follow us on LinkedIn & Twitter Create a Job Alert Interested in building your career at Razorpay Software Private Limited? Get future opportunities sent straight to your email. Create alert Apply for this job * indicates a required field Autofill with MyGreenhouse First Name* Last Name* Email* Phone Country* Phone* Resume/CV* Attach Attach Dropbox Google Drive Enter manually Enter manually Accepted file types: pdf, doc, docx, txt, rtf Employment Company name* Title* Start date month* Select... Start date year* End date month* Select... End date year* Current role Add another LinkedIn Profile* Website* Total Years of Experience* Gender* Select... Current Company* Current Designation* Select... Total Years of Experience* Do you have a valid work permit to work in Malaysia without any visa sponsorship?* Select... What is your current notice period with your employer?* Select... What are your monthly salary expectations in MYR, including any allowances or bonuses (if applicable)? * Submit application Powered by",
    "sections": {
      "about": null,
      "responsibilities": [
        "to",
        "date in the technical knowledge and in",
        "depth understanding of any coding language is a must. Responsible for implementation of the solutions provided by Curlec Razorpay for the Key Clients. Responsible to represent Curlec Razorpay from platform integration perspective with prospective merchants. Accountable to ensure successful implementation of platform integration between Curlec by Razorpay and merchants. Support the reactive queries and requests being raised by Merchants within an agreed turnaround time and quality standards. Read and respond to integration and platform documents shared by prospective customers. The individual will act as a key feedback channel for customer's product"
      ],
      "requirements": [],
      "nice_to_have": [
        "Submit application Powered by"
      ],
      "tech_stack": [
        "Python",
        "JavaScript",
        "Java",
        "REST"
      ],
      "benefits": []
    }
  },
  "scrape_metadata": {
    "scraped_at": "2026-04-16T10:01:19.775888Z",
    "success": true,
    "error": null
  }
}